.gitignore
README.rst
bitbucket-pipelines.yml
setup.cfg
setup.py
fits_validator/__init__.py
fits_validator/base_validator.py
fits_validator/exceptions.py
fits_validator/spec_validators.py
fits_validator.egg-info/PKG-INFO
fits_validator.egg-info/SOURCES.txt
fits_validator.egg-info/dependency_links.txt
fits_validator.egg-info/requires.txt
fits_validator.egg-info/top_level.txt
fits_validator/spec122/__init__.py
fits_validator/spec122/ao.yml
fits_validator/spec122/camera.yml
fits_validator/spec122/cryonirsp.yml
fits_validator/spec122/dkist-dkist.yml
fits_validator/spec122/dkist-id.yml
fits_validator/spec122/dkist-id.yml~
fits_validator/spec122/dl-nirsp.yml
fits_validator/spec122/fits.yml
fits_validator/spec122/fits.yml~
fits_validator/spec122/pac.yml
fits_validator/spec122/vbi.yml
fits_validator/spec122/visp.yml
fits_validator/spec122/vtf.yml
fits_validator/spec122/wcs.yml
fits_validator/spec122/wfc.yml
fits_validator/spec122/ws.yml
fits_validator/spec214/__init__.py
fits_validator/spec214/ao.yml
fits_validator/spec214/camera.yml
fits_validator/tests/__init__.py
fits_validator/tests/test_base_validator.py
fits_validator/tests/test_spec122.py