Metadata-Version: 1.2
Name: fits-validator
Version: 0.3.0
Summary: DKIST fits data validator
Home-page: https://bitbucket.org/dkistdc/dkist_hdr_validator/src/master/
Author: NSO / AURA
Author-email: "aderks@nso.edu"
License: MIT
Platform: UNKNOWN
Classifier: Programming Language :: Python
Classifier: Programming Language :: Python :: 3
Classifier: Programming Language :: Python :: 3.7
Requires-Python: >=3.7
